Metadata-Version: 1.1
Name: abecalculator
Version: 0.2
Summary: A very basic calculator
Home-page: UNKNOWN
Author: ABE Intelligence Group
Author-email: abeintelligencegroup@gmail.com
License: MIT
Keywords: calculator
Platform: UNKNOWN
Classifier: Development Status :: 5 - Production/Stable
Classifier: Intended Audience :: Education
Classifier: Operating System :: Microsoft :: Windows :: Windows 10
Classifier: License :: OSI Approved :: MIT License
Classifier: Programming Language :: Python :: 3
